[{"calorie":0.0,"count":0,"distance":0.0,"speed":0.0},{"calorie":1.2999998331069946,"count":28,"distance":21.399999618530273,"speed":4.437434196472168},{"calorie":0.0,"count":0,"distance":0.0,"speed":0.0},{"calorie":0.0,"count":0,"distance":0.0,"speed":0.0},{"calorie":0.0,"count":0,"distance":0.0,"speed":0.0},{"calorie":0.0,"count":0,"distance":0.0,"speed":0.0},{"calorie":0.0,"count":0,"distance":0.0,"speed":0.0},{"calorie":0.0,"count":0,"distance":0.0,"speed":0.0},{"calorie":0.0,"count":0,"distance":0.0,"speed":0.0},{"calorie":0.0,"count":0,"distance":0.0,"speed":0.0},{"calorie":0.0,"count":0,"distance":0.0,"speed":0.0},{"calorie":0.0,"count":0,"distance":0.0,"speed":0.0},{"calorie":0.0,"count":0,"distance":0.0,"speed":0.0},{"calorie":0.0,"count":0,"distance":0.0,"speed":0.0},{"calorie":0.0,"count":0,"distance":0.0,"speed":0.0},{"calorie":0.0,"count":0,"distance":0.0,"speed":0.0},{"calorie":0.0,"count":0,"distance":0.0,"speed":0.0},{"calorie":0.0,"count":0,"distance":0.0,"speed":0.0},{"calorie":0.0,"count":0,"distance":0.0,"speed":0.0},{"calorie":0.0,"count":0,"distance":0.0,"speed":0.0},{"calorie":0.0,"count":0,"distance":0.0,"speed":0.0},{"calorie":0.0,"count":0,"distance":0.0,"speed":0.0},{"calorie":0.0,"count":0,"distance":0.0,"speed":0.0},{"calorie":0.0,"count":0,"distance":0.0,"speed":0.0},{"calorie":0.0,"count":0,"distance":0.0,"speed":0.0},{"calorie":0.0,"count":0,"distance":0.0,"speed":0.0},{"calorie":0.0,"count":0,"distance":0.0,"speed":0.0},{"calorie":0.0,"count":0,"distance":0.0,"speed":0.0},{"calorie":0.0,"count":0,"distance":0.0,"speed":0.0},{"calorie":0.0,"count":0,"distance":0.0,"speed":0.0},{"calorie":0.0,"count":0,"distance":0.0,"speed":0.0},{"calorie":0.0,"count":0,"distance":0.0,"speed":0.0},{"calorie":0.0,"count":0,"distance":0.0,"speed":0.0},{"calorie":0.0,"count":0,"distance":0.0,"speed":0.0},{"calorie":0.0,"count":0,"distance":0.0,"speed":0.0},{"calorie":0.0,"count":0,"distance":0.0,"speed":0.0},{"calorie":0.0,"count":0,"distance":0.0,"speed":0.0},{"calorie":0.0,"count":0,"distance":0.0,"speed":0.0},{"calorie":0.0,"count":0,"distance":0.0,"speed":0.0},{"calorie":0.0,"count":0,"distance":0.0,"speed":0.0},{"calorie":0.0,"count":0,"distance":0.0,"speed":0.0},{"calorie":0.0,"count":0,"distance":0.0,"speed":0.0},{"calorie":0.0,"count":0,"distance":0.0,"speed":0.0},{"calorie":0.0,"count":0,"distance":0.0,"speed":0.0},{"calorie":0.0,"count":0,"distance":0.0,"speed":0.0},{"calorie":0.0,"count":0,"distance":0.0,"speed":0.0},{"calorie":0.0,"count":0,"distance":0.0,"speed":0.0},{"calorie":0.0,"count":0,"distance":0.0,"speed":0.0},{"calorie":0.0,"count":0,"distance":0.0,"speed":0.0},{"calorie":0.0,"count":0,"distance":0.0,"speed":0.0},{"calorie":0.0,"count":0,"distance":0.0,"speed":0.0},{"calorie":0.0,"count":0,"distance":0.0,"speed":0.0},{"calorie":0.0,"count":0,"distance":0.0,"speed":0.0},{"calorie":2.3500001430511475,"count":48,"distance":36.28000068664551,"speed":4.390862464904785},{"calorie":13.919998407363892,"count":279,"distance":209.16997909545898,"speed":4.185732364654541},{"calorie":9.139999717473984,"count":184,"distance":139.06999254226685,"speed":4.272435665130615},{"calorie":3.990000009536743,"count":80,"distance":59.470001220703125,"speed":3.9872524738311768},{"calorie":0.0,"count":0,"distance":0.0,"speed":0.0},{"calorie":0.0,"count":0,"distance":0.0,"speed":0.0},{"calorie":0.0,"count":0,"distance":0.0,"speed":0.0},{"calorie":0.0,"count":0,"distance":0.0,"speed":0.0},{"calorie":0.0,"count":0,"distance":0.0,"speed":0.0},{"calorie":1.8600000143051147,"count":38,"distance":29.210000038146973,"speed":4.64684534072876},{"calorie":0.9400000274181366,"count":19,"distance":13.989999771118164,"speed":3.671482801437378},{"calorie":0.0,"count":0,"distance":0.0,"speed":0.0},{"calorie":0.0,"count":0,"distance":0.0,"speed":0.0},{"calorie":0.0,"count":0,"distance":0.0,"speed":0.0},{"calorie":0.0,"count":0,"distance":0.0,"speed":0.0},{"calorie":0.0,"count":0,"distance":0.0,"speed":0.0},{"calorie":5.64000016450882,"count":113,"distance":85.27999877929688,"speed":4.276939392089844},{"calorie":0.44999998807907104,"count":9,"distance":6.599999904632568,"speed":3.4000000953674316},{"calorie":27.369999170303345,"count":548,"distance":415.5100040435791,"speed":4.4684648513793945},{"calorie":20.82000032067299,"count":419,"distance":315.4299750328064,"speed":4.220757007598877},{"calorie":0.0,"count":0,"distance":0.0,"speed":0.0},{"calorie":0.0,"count":0,"distance":0.0,"speed":0.0},{"calorie":0.0,"count":0,"distance":0.0,"speed":0.0},{"calorie":0.0,"count":0,"distance":0.0,"speed":0.0},{"calorie":21.33000022172928,"count":427,"distance":327.42000675201416,"speed":4.654480934143066},{"calorie":16.75999980047345,"count":336,"distance":256.5799996852875,"speed":4.607860565185547},{"calorie":0.0,"count":0,"distance":0.0,"speed":0.0},{"calorie":0.0,"count":0,"distance":0.0,"speed":0.0},{"calorie":0.0,"count":0,"distance":0.0,"speed":0.0},{"calorie":0.0,"count":0,"distance":0.0,"speed":0.0},{"calorie":0.0,"count":0,"distance":0.0,"speed":0.0},{"calorie":4.090000033378601,"count":82,"distance":60.209999084472656,"speed":3.5796420574188232},{"calorie":0.0,"count":0,"distance":0.0,"speed":0.0},{"calorie":0.0,"count":0,"distance":0.0,"speed":0.0},{"calorie":3.2700001001358032,"count":66,"distance":49.24000072479248,"speed":3.9685556888580322},{"calorie":0.0,"count":0,"distance":0.0,"speed":0.0},{"calorie":0.0,"count":0,"distance":0.0,"speed":0.0},{"calorie":2.5299999713897705,"count":51,"distance":38.31999969482422,"speed":4.199999809265137},{"calorie":0.0,"count":0,"distance":0.0,"speed":0.0},{"calorie":0.0,"count":0,"distance":0.0,"speed":0.0},{"calorie":0.0,"count":0,"distance":0.0,"speed":0.0},{"calorie":3.759999990463257,"count":76,"distance":57.260000228881836,"speed":4.338006019592285},{"calorie":2.740000009536743,"count":55,"distance":41.19999885559082,"speed":4.125813007354736},{"calorie":0.0,"count":0,"distance":0.0,"speed":0.0},{"calorie":2.249999523162842,"count":45,"distance":33.6400032043457,"speed":4.129263877868652},{"calorie":0.75,"count":15,"distance":11.309999465942383,"speed":4.244333744049072},{"calorie":0.6499999761581421,"count":13,"distance":9.479999542236328,"speed":3.700000047683716},{"calorie":2.290000021457672,"count":46,"distance":34.55000019073486,"speed":4.199999809265137},{"calorie":2.059999942779541,"count":41,"distance":30.09000015258789,"speed":3.799999952316284},{"calorie":3.399999737739563,"count":68,"distance":49.76999521255493,"speed":3.5649776458740234},{"calorie":0.0,"count":0,"distance":0.0,"speed":0.0},{"calorie":0.0,"count":0,"distance":0.0,"speed":0.0},{"calorie":4.990000128746033,"count":100,"distance":74.34999656677246,"speed":3.9009485244750977},{"calorie":0.0,"count":0,"distance":0.0,"speed":0.0},{"calorie":0.0,"count":0,"distance":0.0,"speed":0.0},{"calorie":0.0,"count":0,"distance":0.0,"speed":0.0},{"calorie":3.7800000607967377,"count":76,"distance":56.8299994468689,"speed":4.126137733459473},{"calorie":8.689999461174011,"count":175,"distance":131.45000171661377,"speed":4.100122451782227},{"calorie":1.0399999618530273,"count":21,"distance":15.9399995803833,"speed":4.5},{"calorie":14.339998424053192,"count":289,"distance":213.81999683380127,"speed":3.838094711303711},{"calorie":2.439999997615814,"count":49,"distance":36.52000045776367,"speed":4.034885406494141},{"calorie":6.70000022649765,"count":134,"distance":99.92999744415283,"speed":3.964592933654785},{"calorie":11.109999120235443,"count":223,"distance":168.76999855041504,"speed":4.27311897277832},{"calorie":3.0800000429153442,"count":63,"distance":48.52999782562256,"speed":4.752641677856445},{"calorie":0.0,"count":0,"distance":0.0,"speed":0.0},{"calorie":1.7399998307228088,"count":35,"distance":26.969999313354492,"speed":4.636546611785889},{"calorie":0.8400000035762787,"count":17,"distance":13.129999160766602,"speed":4.960097312927246},{"calorie":0.49000000953674316,"count":10,"distance":7.789999961853027,"speed":5.099999904632568},{"calorie":3.1500001549720764,"count":63,"distance":46.35999870300293,"speed":3.68843412399292},{"calorie":0.0,"count":0,"distance":0.0,"speed":0.0},{"calorie":0.0,"count":0,"distance":0.0,"speed":0.0},{"calorie":0.0,"count":0,"distance":0.0,"speed":0.0},{"calorie":0.0,"count":0,"distance":0.0,"speed":0.0},{"calorie":0.0,"count":0,"distance":0.0,"speed":0.0},{"calorie":0.0,"count":0,"distance":0.0,"speed":0.0},{"calorie":0.0,"count":0,"distance":0.0,"speed":0.0},{"calorie":0.0,"count":0,"distance":0.0,"speed":0.0},{"calorie":0.0,"count":0,"distance":0.0,"speed":0.0},{"calorie":0.0,"count":0,"distance":0.0,"speed":0.0},{"calorie":0.0,"count":0,"distance":0.0,"speed":0.0},{"calorie":0.0,"count":0,"distance":0.0,"speed":0.0},{"calorie":0.0,"count":0,"distance":0.0,"speed":0.0},{"calorie":0.0,"count":0,"distance":0.0,"speed":0.0},{"calorie":0.0,"count":0,"distance":0.0,"speed":0.0},{"calorie":0.0,"count":0,"distance":0.0,"speed":0.0},{"calorie":0.0,"count":0,"distance":0.0,"speed":0.0},{"calorie":0.0,"count":0,"distance":0.0,"speed":0.0},{"calorie":0.0,"count":0,"distance":0.0,"speed":0.0},{"calorie":27.860000610351562,"count":558,"distance":420.5,"speed":4.297308921813965},{"calorie":24.399999678134918,"count":488,"distance":369.4900007247925,"speed":4.450432300567627},{"calorie":0.0,"count":0,"distance":0.0,"speed":0.0}]